flowframe/__init__.py
flowframe/flowframe.py
flowframe-0.0.1.dist-info/LICENSE
flowframe-0.0.1.dist-info/METADATA
flowframe-0.0.1.dist-info/WHEEL
flowframe-0.0.1.dist-info/top_level.txt
flowframe-0.0.1.dist-info/RECORD
