Metadata-Version: 2.1
Name: flowframe
Version: 0.0.1
Summary: This module makes a FlowFrame which inherits from the Frame class in tkinter
Home-page: https://github.com/garydavenport73/FlowFrame
Author: Gary Davenport
Author-email: dovedweller@gmail.com
License: UNKNOWN
Project-URL: Bug Tracker, https://github.com/garydavenport73/FlowFrame/issues
Platform: UNKNOWN
Classifier: Programming Language :: Python :: 3
Classifier: License :: OSI Approved :: MIT License
Classifier: Operating System :: OS Independent
Requires-Python: >=3.6
License-File: LICENSE
